{"agrimensura": [2, "/categories/agrimensura/", {"posts": [{"date": "10/06/2015", "isodate": "2015-10-06T12:00:00+00:00", "title": "Aportes de la Agrimensura a la actividad agr\u00edcola", "url": "/blog/aportes-agrim/"}, {"date": "10/06/2015", "isodate": "2015-10-06T11:00:00+00:00", "title": "La medida", "url": "/blog/la-medida/"}]}], "enia": [1, "/categories/enia/", {"posts": [{"date": "06/04/2016", "isodate": "2016-06-04T20:07:22-03:00", "title": "ENIA 2016", "url": "/blog/enia-2016/"}]}], "galvez": [1, "/categories/galvez/", {"posts": [{"date": "05/01/2016", "isodate": "2016-05-01T19:54:53-03:00", "title": "El Ordenamiento Territorial de G\u00e1lvez", "url": "/blog/galvez-ot/"}]}], "ggsr": [1, "/categories/ggsr/", {"posts": [{"date": "06/04/2016", "isodate": "2016-06-04T20:07:22-03:00", "title": "ENIA 2016", "url": "/blog/enia-2016/"}]}], "medici\u00f3n": [1, "/categories/medicion/", {"posts": [{"date": "10/06/2015", "isodate": "2015-10-06T11:00:00+00:00", "title": "La medida", "url": "/blog/la-medida/"}]}], "ordenamiento territorial": [1, "/categories/ordenamiento-territorial/", {"posts": [{"date": "05/01/2016", "isodate": "2016-05-01T19:54:53-03:00", "title": "El Ordenamiento Territorial de G\u00e1lvez", "url": "/blog/galvez-ot/"}]}], "ppp": [1, "/categories/ppp/", {"posts": [{"date": "06/04/2016", "isodate": "2016-06-04T20:07:22-03:00", "title": "ENIA 2016", "url": "/blog/enia-2016/"}]}], "precisi\u00f3n": [1, "/categories/precision/", {"posts": [{"date": "10/06/2015", "isodate": "2015-10-06T11:00:00+00:00", "title": "La medida", "url": "/blog/la-medida/"}]}]}